supsmu/_supsmu.cpython-313-x86_64-linux-gnu.so
supsmu/_supsmu.pyi
supsmu/__init__.py
supsmu/_supsmu.pyx
supsmu/supsmu.h
supsmu/supsmu.c
supsmu/_supsmu.c
supsmu-1.1.0.dist-info/METADATA
supsmu-1.1.0.dist-info/RECORD
supsmu-1.1.0.dist-info/top_level.txt
supsmu-1.1.0.dist-info/WHEEL
supsmu-1.1.0.dist-info/LICENSE
