Metadata-Version: 2.2
Name: supsmu
Version: 1.1.0
Summary: Efficient SuperSmoother for Python
Author-email: Tux Type <tuxtyped@gmail.com>
License: MIT License
Classifier: Intended Audience :: Science/Research
Classifier: License :: OSI Approved :: MIT License
Classifier: Programming Language :: Python :: 3
Classifier: Programming Language :: Cython
Classifier: Programming Language :: C
Requires-Python: >=3.10
License-File: LICENSE
Requires-Dist: numpy>=1.20.0
Requires-Dist: cython>=3.0.11
